lxml_xpath_utils.py
lxml_xpath_utils-0.1.1.dist-info/licenses/LICENSE
lxml_xpath_utils-0.1.1.dist-info/METADATA
lxml_xpath_utils-0.1.1.dist-info/WHEEL
lxml_xpath_utils-0.1.1.dist-info/top_level.txt
lxml_xpath_utils-0.1.1.dist-info/RECORD
