Metadata-Version: 2.4
Name: lxml-xpath-utils
Version: 0.1.1
Summary: A collection of utility functions for working with lxml and XPath.
Author-email: Jifeng Wu <jifengwu2k@gmail.com>
License-Expression: MIT
Project-URL: Homepage, https://github.com/jifengwu2k/lxml-xpath-utils
Project-URL: Bug Tracker, https://github.com/jifengwu2k/lxml-xpath-utils/issues
Classifier: Programming Language :: Python :: 2
Classifier: Programming Language :: Python :: 3
Classifier: Operating System :: OS Independent
Requires-Python: >=2
License-File: LICENSE
Requires-Dist: lxml
Dynamic: license-file
